{
  "rows": 11,
  "columns": 15,
  "0,0": "Mildura",
  "0,1": "Lowan",
  "0,2": "Wendouree",
  "0,3": "Buninyong",
  "0,4": "Sunbury",
  "0,5": "Sydenham",
  "0,6": "Kororoit",
  "0,7": "Tarneit",
  "0,8": "South-West Coast",
  "1,0": "Murray Plains",
  "1,1": "Ripon",
  "1,2": "Melton",
  "1,3": "Yuroke",
  "1,4": "Niddrie",
  "1,5": "Essendon",
  "1,6": "St Albans",
  "1,7": "Footscray",
  "1,8": "Werribee",
  "2,1": "Bendigo West",
  "2,2": "Macedon",
  "2,3": "Broadmeadows",
  "2,4": "Pascoe Vale",
  "2,5": "Brunswick",
  "2,6": "Melbourne",
  "2,7": "Williamstown",
  "2,8": "Altona",
  "2,9": "Polwarth",
  "3,2": "Bendigo East",
  "3,3": "Thomastown",
  "3,4": "Preston",
  "3,5": "Northcote",
  "3,6": "Richmond",
  "3,7": "Caulfield",
  "3,8": "Prahran",
  "3,9": "Lara",
  "3,10": "South Barwon",
  "4,3": "Mill Park",
  "4,4": "Bundoora",
  "4,5": "Kew",
  "4,6": "Hawthorn",
  "4,7": "Malvern",
  "4,8": "Albert Park",
  "4,9": "Geelong",
  "5,3": "Eltham",
  "5,4": "Ivanhoe",
  "5,5": "Bulleen",
  "5,6": "Burwood",
  "5,7": "Brighton",
  "5,9": "Bellarine",
  "6,4": "Box Hill",
  "6,5": "Forest Hill",
  "6,6": "Sandringham",
  "7,3": "Shepparton",
  "7,4": "Warrandyte",
  "7,5": "Mount Waverley",
  "7,6": "Bentleigh",
  "7,9": "Nepean",
  "8,3": "Euroa",
  "8,4": "Croydon",
  "8,5": "Ringwood",
  "8,6": "Oakleigh",
  "8,7": "Mordialloc",
  "8,8": "Frankston",
  "8,9": "Mornington",
  "9,3": "Eildon",
  "9,4": "Yan Yean",
  "9,5": "Bayswater",
  "9,6": "Clarinda",
  "9,7": "Keysborough",
  "9,8": "Carrum",
  "9,9": "Hastings",
  "9,10": "Bass",
  "10,4": "Ovens Valley",
  "10,5": "Ferntree Gully",
  "10,6": "Mulgrave",
  "10,7": "Dandenong",
  "10,8": "Cranbourne",
  "10,9": "Gippsland South",
  "11,5": "Benambra",
  "11,6": "Rowville",
  "11,7": "Narre Warren North",
  "11,8": "Narre Warren South",
  "12,5": "Evelyn",
  "12,6": "Monbulk",
  "12,7": "Narracan",
  "13,6": "Gembrook",
  "13,7": "Morwell",
  "14,6": "Gippsland East"
}
